{
  "run_dir": "20260607_063758_navigate-to-the-clothes-dryer_scene280",
  "started_at": "2026-06-07T07:34:59",
  "task": "Navigate to the Clothes Dryer",
  "scene_index": 280,
  "steps": 50,
  "florence_model": "microsoft/Florence-2-base",
  "sam_weights": "sam2_b.pt",
  "device": "auto",
  "tritonai": true,
  "headless_perception": false,
  "completed_steps": 50,
  "finished_at": "2026-06-07T07:34:59",
  "action_history": [
    "controller.step(action='RotateLeft', degrees=90)",
    "controller.step(action='RotateRight', degrees=90)",
    "controller.step(action='RotateLeft', degrees=90)",
    "controller.step(action='RotateLeft', degrees=90)",
    "controller.step(action='RotateLeft', degrees=90)",
    "controller.step(action='RotateRight', degrees=90)",
    "controller.step(action='RotateRight', degrees=90)",
    "controller.step(action='RotateRight', degrees=90)",
    "controller.step(action='MoveAhead', moveMagnitude=1.0)",
    "controller.step(action='RotateRight', degrees=90)",
    "controller.step(action='RotateLeft', degrees=90)",
    "controller.step(action='RotateRight', degrees=90)",
    "controller.step(action='RotateLeft', degrees=90)",
    "controller.step(action='RotateLeft', degrees=90)",
    "controller.step(action='RotateLeft', degrees=90)",
    "controller.step(action='MoveAhead', moveMagnitude=1.0)",
    "controller.step(action='RotateRight', degrees=90)",
    "controller.step(action='RotateRight', degrees=90)",
    "controller.step(action='RotateLeft', degrees=90)",
    "controller.step(action='RotateRight', degrees=30)",
    "controller.step(action='RotateLeft', degrees=90)",
    "controller.step(action='MoveAhead', moveMagnitude=1.0)",
    "controller.step(action='MoveAhead', moveMagnitude=1.0) [FAILED: wall|4|8.20|10.25|8.20|14.35 is blocking Agent 0 from moving by (-0.8660, 0.0000, 0.5000).]",
    "controller.step(action='MoveAhead', moveMagnitude=0.5)",
    "controller.step(action='RotateRight', degrees=90)",
    "controller.step(action='RotateRight', degrees=90)",
    "controller.step(action='RotateLeft', degrees=90)",
    "controller.step(action='RotateRight', degrees=90)",
    "controller.step(action='RotateLeft', degrees=90)",
    "controller.step(action='RotateLeft', degrees=90)",
    "controller.step(action='RotateLeft', degrees=90)",
    "controller.step(action='MoveAhead', moveMagnitude=0.5) [FAILED: Sofa|4|2 is blocking Agent 0 from moving by (-0.2500, 0.0000, -0.4330).]",
    "controller.step(action='RotateLeft', degrees=30)",
    "controller.step(action='RotateRight', degrees=90)",
    "controller.step(action='RotateLeft', degrees=90)",
    "controller.step(action='RotateLeft', degrees=90)",
    "controller.step(action='RotateRight', degrees=90)",
    "controller.step(action='RotateLeft', degrees=90)",
    "controller.step(action='RotateLeft', degrees=90)",
    "controller.step(action='RotateLeft', degrees=90)",
    "controller.step(action='RotateLeft', degrees=90)",
    "controller.step(action='RotateRight', degrees=90)",
    "controller.step(action='RotateRight', degrees=90)",
    "controller.step(action='RotateLeft', degrees=90)",
    "controller.step(action='RotateLeft', degrees=90)",
    "controller.step(action='RotateLeft', degrees=90)",
    "controller.step(action='RotateLeft', degrees=90)",
    "controller.step(action='RotateLeft', degrees=90)",
    "controller.step(action='RotateLeft', degrees=90)",
    "controller.step(action='RotateLeft', degrees=90)",
    "controller.step(action='RotateLeft', degrees=90)",
    "controller.step(action='RotateLeft', degrees=90)"
  ],
  "success": false,
  "actual_path_length": 3.460404813240945,
  "shortest_path_length": 0.25,
  "critic_aborted": false
}